hostname_resolver/__init__.py
hostname_resolver/custom_datatypes/__init__.py
hostname_resolver/custom_datatypes/frozentemplate/__init__.py
hostname_resolver/custom_datatypes/gatherunique/__init__.py
hostname_resolver/custom_datatypes/tablemat/__init__.py
hostname_resolver/custom_datatypes/threaded_file_handler/__init__.py
hostname_resolver/reference_data/__init__.py
hostname_resolver/reference_data/_constants.py
hostname_resolver/reference_data/_ip_rep.py
hostname_resolver/reference_data/_settings.py
hostname_resolver/reporter_helper/__init__.py
hostname_resolver/reporter_helper/_report_amanager.py
hostname_resolver/reporter_helper/_report_csv.py
hostname_resolver/reporter_helper/_report_single_file.py
hostname_resolver/reporter_helper/_report_zengine.py
hostname_resolver-0.1.0.dist-info/LICENSE
hostname_resolver-0.1.0.dist-info/METADATA
hostname_resolver-0.1.0.dist-info/WHEEL
hostname_resolver-0.1.0.dist-info/top_level.txt
hostname_resolver-0.1.0.dist-info/RECORD
