Metadata-Version: 2.1
Name: hostname-resolver
Version: 0.1.0
Summary: A bulk hostname resolver, against known TLDs
Home-page: https://github.com/dpazavalos/bulk-hostname-scanner
Author: Daniel Paz Avalos
Author-email: me@dpazavalos.dev
License: UNKNOWN
Platform: UNKNOWN
Classifier: Programming Language :: Python :: 3
Classifier: License :: OSI Approved :: MIT License
Classifier: Operating System :: OS Independent
